nltk_pos_tag_mapping_to_wn_lematizer/__init__.py
nltk_pos_tag_mapping_to_wn_lematizer/mapping.py
postagwordnet-0.0.3.dist-info/METADATA
postagwordnet-0.0.3.dist-info/WHEEL
postagwordnet-0.0.3.dist-info/top_level.txt
postagwordnet-0.0.3.dist-info/RECORD
