Metadata-Version: 2.1
Name: postagwordnet
Version: 0.0.3
Summary: Mapping Pos Tags To Recognized WordNet Lemetaizer categories
Author: Michael Mansour
Author-email: <michael.mansour@cis.asu.edu.eg>
Keywords: python,nlp,nltk,pos-tag,mapping,wordnet,lemmatization
Classifier: Development Status :: 1 - Planning
Classifier: Intended Audience :: Developers
Classifier: Programming Language :: Python :: 3
Classifier: Operating System :: Unix
Classifier: Operating System :: MacOS :: MacOS X
Classifier: Operating System :: Microsoft :: Windows
Requires-Dist: nltk >=3.5
